Metadata-Version: 2.1
Name: wrktools
Version: 0.1.9
Summary: A tool to run wrk and wrk2 benchmarks and store their output.
Home-page: https://github.com/RobertoPrevato/wrktoolbox
Author: RobertoPrevato
Author-email: roberto.prevato@gmail.com
License: MIT
Keywords: wrk runner benchmarks load performance tests
Platform: UNKNOWN
Classifier: Development Status :: 5 - Production/Stable
Classifier: License :: OSI Approved :: MIT License
Classifier: Programming Language :: Python :: 3
Classifier: Operating System :: Unix
Requires-Dist: pyparsing
Requires-Dist: rocore
Requires-Dist: roconfiguration
Requires-Dist: click
Requires-Dist: certifi
